{"cameraMode":{"drawMode":0,"name":"Shaded","section":"Shading Mode"},"sceneLighting":true,"audioPlay":false,"sceneViewState":{"showFog":true,"showMaterialUpdate":false,"showSkybox":true,"showFlares":true,"showImageEffects":true,"showParticleSystems":true},"in2DMode":false,"pivot":{"x":3.7256393432617189,"y":1.6006345748901368,"z":-13.467769622802735},"rotation":{"x":0.2505422532558441,"y":0.24364392459392548,"z":-0.06530950218439102,"w":0.9346662163734436},"size":15.567410469055176,"orthographic":false}